pyemblite/__init__.py
pyemblite/_version.py
pyemblite/mesh_construction.py
pyemblite/rtcore.py
pyemblite/rtcore_scene.py
pyemblite/test.py
pyemblite/test_scene.py
pyemblite/utils.py
pyemblite/embree3/__init__.py
pyemblite/embree4/__init__.py
pyemblite/embree4/mesh_construction4.cpython-312-darwin.so
pyemblite/embree4/rtcore4.cpython-312-darwin.so
pyemblite/embree4/rtcore_scene4.cpython-312-darwin.so
pyemblite/embree4/test_scene4.cpython-312-darwin.so
pyemblite-0.2.9.dist-info/licenses/LICENSE.txt
pyemblite-0.2.9.dist-info/METADATA
pyemblite-0.2.9.dist-info/WHEEL
pyemblite-0.2.9.dist-info/top_level.txt
pyemblite-0.2.9.dist-info/RECORD
