Metadata-Version: 2.4
Name: pyemblite
Version: 0.2.9
Summary: Python wrapper for Embree-3.
Author: Shane-J-Latham, Department of Materials Physics, ANU
License: Copyright (c) 2015, Anthony Scopatz
Project-URL: Homepage, https://github.com/AppliedMathematicsANU/pyemblite/
Project-URL: Repository, https://github.com/AppliedMathematicsANU/pyemblite/
Project-URL: Issues, https://github.com/AppliedMathematicsANU/pyemblite/issues
Keywords: embree,embree3,embree-3,ray-casting
Classifier: Programming Language :: Python :: 3
Classifier: License :: OSI Approved :: BSD License
Classifier: Operating System :: OS Independent
Requires-Python: >=3.8
License-File: LICENSE.txt
Requires-Dist: numpy>=1.14.5
Dynamic: license-file
